ragbee_fw/__init__.py
ragbee_fw/cli.py
ragbee_fw/config/app_config.yml
ragbee_fw/config/load_config.py
ragbee_fw/core/models/__init__.py
ragbee_fw/core/models/app_config.py
ragbee_fw/core/models/document.py
ragbee_fw/core/ports/__init__.py
ragbee_fw/core/ports/data_loader_port.py
ragbee_fw/core/ports/llm_port.py
ragbee_fw/core/ports/retriever_port.py
ragbee_fw/core/ports/splitter_port.py
ragbee_fw/core/services/__init__.py
ragbee_fw/core/services/answer_service.py
ragbee_fw/core/services/ingestion_service.py
ragbee_fw/infrastructure/__init__.py
ragbee_fw/infrastructure/data_loader/__init__.py
ragbee_fw/infrastructure/data_loader/file_loader.py
ragbee_fw/infrastructure/di_conteiner/di_conteiner.py
ragbee_fw/infrastructure/llm_clients/__init__.py
ragbee_fw/infrastructure/llm_clients/huggingface_client.py
ragbee_fw/infrastructure/retriever/__init__.py
ragbee_fw/infrastructure/retriever/bm25_client.py
ragbee_fw/infrastructure/text_splitter/__init__.py
ragbee_fw/infrastructure/text_splitter/recursive_text_splitter.py
ragbee_fw-0.1.3.dist-info/METADATA
ragbee_fw-0.1.3.dist-info/WHEEL
ragbee_fw-0.1.3.dist-info/entry_points.txt
ragbee_fw-0.1.3.dist-info/RECORD
