Metadata-Version: 2.3
Name: ragbee-fw
Version: 0.1.3
Summary: Lightweight RAG framework
License: MIT
Keywords: rag,llm,retrieval,framework
Author: shevchenko v.a.
Author-email: droogg@mail.ru
Requires-Python: >=3.10
Classifier: License :: OSI Approved :: MIT License
Classifier: Programming Language :: Python :: 3
Classifier: Programming Language :: Python :: 3.10
Classifier: Programming Language :: Python :: 3.11
Classifier: Programming Language :: Python :: 3.12
Classifier: Programming Language :: Python :: 3.13
Requires-Dist: charset-normalizer (>=3.4.2,<4.0.0)
Requires-Dist: huggingface-hub (>=0.31.1,<0.32.0)
Requires-Dist: openai (>=1.97.0,<2.0.0)
Requires-Dist: pydantic (>=2.11.7,<3.0.0)
Requires-Dist: rank-bm25 (>=0.2.2,<0.3.0)
Requires-Dist: typer (>=0.15.4,<0.16.0)
Project-URL: Homepage, https://github.com/droogg/ragbee_fw
Project-URL: Repository, https://github.com/droogg/ragbee_fw
